skybaks/roll_dice/__init__.py
pyplanet_roll_dice-1.1.1.dist-info/METADATA
pyplanet_roll_dice-1.1.1.dist-info/WHEEL
pyplanet_roll_dice-1.1.1.dist-info/RECORD
